GSOF_ArduBridge/ArduAnalog.py
GSOF_ArduBridge/ArduBridge.py
GSOF_ArduBridge/ArduGPIO.py
GSOF_ArduBridge/ArduI2C.py
GSOF_ArduBridge/ArduPulseAndSample.py
GSOF_ArduBridge/ArduSPI.py
GSOF_ArduBridge/ArduShield_Uno.py
GSOF_ArduBridge/ArduWs2812.py
GSOF_ArduBridge/BridgeSerial.py
GSOF_ArduBridge/Buzzer.py
GSOF_ArduBridge/ExtGpio_base.py
GSOF_ArduBridge/PidAlgorithm.py
GSOF_ArduBridge/Pin_class.py
GSOF_ArduBridge/S_Curve.py
GSOF_ArduBridge/Sleep_us.py
GSOF_ArduBridge/UDP_Send.py
GSOF_ArduBridge/UdpToConViewer.py
GSOF_ArduBridge/__init__.py
GSOF_ArduBridge/movAvg.py
GSOF_ArduBridge/threadBasic.py
GSOF_ArduBridge/threadElectrodeSeq.py
GSOF_ArduBridge/threadPID.py
GSOF_ArduBridge/threadPID_HW11.py
GSOF_ArduBridge/udpControl.py
GSOF_ArduBridge/device/AD7747_class.py
GSOF_ArduBridge/device/ADXL345_RM.py
GSOF_ArduBridge/device/ADXL345_class.py
GSOF_ArduBridge/device/BH1750_class.py
GSOF_ArduBridge/device/BMP085_RM.py
GSOF_ArduBridge/device/BMP085_class.py
GSOF_ArduBridge/device/DS3231_RM.py
GSOF_ArduBridge/device/HMC5883_RM.py
GSOF_ArduBridge/device/HMC5883_class.py
GSOF_ArduBridge/device/HVSW_Driver_V1.py
GSOF_ArduBridge/device/HVSW_Driver_V2.py
GSOF_ArduBridge/device/HVSW_Driver_base.py
GSOF_ArduBridge/device/HVSW_Stack.py
GSOF_ArduBridge/device/MPU6050_RM.py
GSOF_ArduBridge/device/MPU6050_class.py
GSOF_ArduBridge/device/SSD1306_class.py
GSOF_ArduBridge/device/Servo.py
GSOF_ArduBridge/device/TMC5130_class.py
GSOF_ArduBridge/device/__init__.py
GSOF_ArduBridge/device/ad9833_class.py
GSOF_ArduBridge/device/ads1115_class.py
GSOF_ArduBridge/device/ads1x15_class.py
GSOF_ArduBridge/device/blinkM_class.py
GSOF_ArduBridge/device/charLCD.py
GSOF_ArduBridge/device/ds3231_class.py
GSOF_ArduBridge/device/epd2in7_class.py
GSOF_ArduBridge/device/epd4in2_class.py
GSOF_ArduBridge/device/max7300_class.py
GSOF_ArduBridge/device/pca9505_class.py
GSOF_ArduBridge/device/pca9685_class.py
GSOF_ArduBridge/device/pcf8574_class.py
GSOF_ArduBridge/device/pcf8591_class.py
GSOF_ArduBridge-0.13.dist-info/AUTHORS
GSOF_ArduBridge-0.13.dist-info/LICENSE.txt
GSOF_ArduBridge-0.13.dist-info/METADATA
GSOF_ArduBridge-0.13.dist-info/WHEEL
GSOF_ArduBridge-0.13.dist-info/top_level.txt
GSOF_ArduBridge-0.13.dist-info/RECORD
